ml2rt/__init__.py
ml2rt/exporter.py
ml2rt/importer.py
ml2rt/utils.py
ml2rt/version.py
ml2rt-0.2.0.dist-info/AUTHORS.rst
ml2rt-0.2.0.dist-info/LICENSE
ml2rt-0.2.0.dist-info/METADATA
ml2rt-0.2.0.dist-info/WHEEL
ml2rt-0.2.0.dist-info/top_level.txt
ml2rt-0.2.0.dist-info/RECORD
