Metadata-Version: 2.1
Name: ml2rt
Version: 0.2.0
Summary: Machine learning utilities for model conversion, serialization, loading etc
Home-page: https://github.com/hhsecond/ml2rt
Author: Sherin Thomas
Author-email: sherin@tensorwerk.com
License: Apache Software License 2.0
Keywords: ml2rt
Platform: UNKNOWN
Classifier: Development Status :: 2 - Pre-Alpha
Classifier: Intended Audience :: Developers
Classifier: License :: OSI Approved :: Apache Software License
Classifier: Natural Language :: English
Classifier: Programming Language :: Python :: 3
Classifier: Programming Language :: Python :: 3 :: Only
Classifier: Programming Language :: Python :: 3.6
Classifier: Programming Language :: Python :: 3.7
Provides-Extra: all
Requires-Dist: tensorflow ; extra == 'all'
Requires-Dist: torch ; extra == 'all'
Requires-Dist: sklearn ; extra == 'all'
Requires-Dist: skl2onnx ; extra == 'all'
Requires-Dist: pandas ; extra == 'all'
Requires-Dist: onnxmltools ; extra == 'all'
Requires-Dist: onnxconverter-common ; extra == 'all'
Requires-Dist: numpy ; extra == 'all'
Requires-Dist: pyspark ; extra == 'all'
Requires-Dist: onnx ; extra == 'all'
Provides-Extra: onnx
Requires-Dist: onnx ; extra == 'onnx'
Provides-Extra: pytorch
Requires-Dist: torch ; extra == 'pytorch'
Provides-Extra: sklearn
Requires-Dist: sklearn ; extra == 'sklearn'
Requires-Dist: skl2onnx ; extra == 'sklearn'
Requires-Dist: pandas ; extra == 'sklearn'
Requires-Dist: onnxmltools ; extra == 'sklearn'
Requires-Dist: onnxconverter-common ; extra == 'sklearn'
Requires-Dist: numpy ; extra == 'sklearn'
Provides-Extra: sparkml
Requires-Dist: pyspark ; extra == 'sparkml'
Requires-Dist: onnxmltools ; extra == 'sparkml'
Requires-Dist: onnxconverter-common ; extra == 'sparkml'
Requires-Dist: numpy ; extra == 'sparkml'
Provides-Extra: tensorflow
Requires-Dist: tensorflow ; extra == 'tensorflow'
